man2text/_version.py
man2text/cli.py
man2text/core.py
man2text/discover.py
man2text/init.py
man2text/main.py
man2text/render.py
man2text/utils.py
man2text-0.5.0.dist-info/METADATA
man2text-0.5.0.dist-info/WHEEL
man2text-0.5.0.dist-info/entry_points.txt
man2text-0.5.0.dist-info/top_level.txt
man2text-0.5.0.dist-info/RECORD
