Metadata-Version: 2.4
Name: man2text
Version: 0.5.0
Summary: Convert system manpages to plain UTF-8 text files (English-only by default).
Author: Your Name
Project-URL: Homepage, https://github.com/udqy/man2text
Classifier: License :: OSI Approved :: MIT License
Classifier: Programming Language :: Python :: 3
Classifier: Operating System :: POSIX :: Linux
Requires-Python: >=3.8
Requires-Dist: tqdm
